{
    "feature_importances": [
        {
            "feature": "BMI <= 0.39",
            "importance": 0.04611732115450458
        },
        {
            "feature": "Weight <= 0.24",
            "importance": 0.03758570885169007
        },
        {
            "feature": "Height <= 0.54",
            "importance": -0.01514304528746432
        },
        {
            "feature": "0.50 < Gender <= 1.00",
            "importance": -0.002431473709058611
        },
        {
            "feature": "Age <= 0.27",
            "importance": -4.0120645864402876e-05
        }
    ],
    "intercept": {
        "1": -0.0051666235791238795
    },
    "feature_values": {
        "Weight": 70.0,
        "Height": 1.75,
        "BMI": 24.5,
        "Age": 35.0,
        "Gender": "Male"
    }
}